acousticDE/__init__.py
acousticDE/Auralization/Auralization.py
acousticDE/Auralization/Auralizationfunctions.py
acousticDE/Auralization/__init__.py
acousticDE/Auralization/tests/Frequency(english).wav
acousticDE/Auralization/tests/resultsFVM.pkl
acousticDE/Auralization/tests/test_run_auralization_sim.py
acousticDE/FiniteDifferenceMethod/FDM.py
acousticDE/FiniteDifferenceMethod/FDMfunctions.py
acousticDE/FiniteDifferenceMethod/FunctionCentreTime.py
acousticDE/FiniteDifferenceMethod/FunctionClarity.py
acousticDE/FiniteDifferenceMethod/FunctionDefinition.py
acousticDE/FiniteDifferenceMethod/FunctionRT.py
acousticDE/FiniteDifferenceMethod/PrepareInputsFDM.py
acousticDE/FiniteDifferenceMethod/__init__.py
acousticDE/FiniteDifferenceMethod/tests/test_run_fdm_sim.py
acousticDE/FiniteVolumeMethod/CreateGeoFVM.py
acousticDE/FiniteVolumeMethod/CreateMeshFVM.py
acousticDE/FiniteVolumeMethod/FVM.py
acousticDE/FiniteVolumeMethod/FVMfunctions.py
acousticDE/FiniteVolumeMethod/FunctionCentreTime.py
acousticDE/FiniteVolumeMethod/FunctionClarity.py
acousticDE/FiniteVolumeMethod/FunctionDefinition.py
acousticDE/FiniteVolumeMethod/FunctionRT.py
acousticDE/FiniteVolumeMethod/PrepareInputsFVM.py
acousticDE/FiniteVolumeMethod/__init__.py
acousticDE/FiniteVolumeMethod/resultsFVM.pkl
acousticDE/FiniteVolumeMethod/.ipynb_checkpoints/FVMfunctions-checkpoint.py
acousticDE/FiniteVolumeMethod/tests/test_abs_coeff.csv
acousticDE/FiniteVolumeMethod/tests/test_mesh.msh
acousticDE/FiniteVolumeMethod/tests/test_run_fvm_sim.py
acousticde-0.1.0.dist-info/licenses/LICENSE.md
acousticde-0.1.0.dist-info/WHEEL
acousticde-0.1.0.dist-info/METADATA
acousticde-0.1.0.dist-info/RECORD
