Metadata-Version: 2.4
Name: acousticDE
Version: 0.1.0
Summary: Acoustics Simulation using the Diffusion Equation
Keywords: room acoustics,acoustic diffusion equation,acoustic simulations
Author-email: Ilaria Fichera <i.fichera@tue.nl>, Cedric Van hoorickx <c.m.l.van.hoorickx@tue.nl>, Maarten Hoornikx <m.c.j.hornikx@tue.nl>
Requires-Python: >=3.10
Classifier: Development Status :: 4 - Beta
Classifier: Intended Audience :: Science/Research
Classifier: License :: OSI Approved :: GNU General Public License v2 (GPLv2)
Classifier: Natural Language :: English
Classifier: Programming Language :: Python :: 3
Classifier: Programming Language :: Python :: 3.10
License-File: LICENSE.md
Requires-Dist: numpy<2.0.0
Requires-Dist: scipy
Requires-Dist: gmsh
Requires-Dist: soundfile
Requires-Dist: sounddevice
Requires-Dist: pandas
Requires-Dist: pytest
Requires-Dist: acousticDE[docs] ; extra == "dev"
Requires-Dist: sphinx ; extra == "docs"
Requires-Dist: sphinx-rtd-theme ; extra == "docs"
Requires-Dist: myst_parser ; extra == "docs"
Requires-Dist: sphinx-gallery ; extra == "docs"
Requires-Dist: pooch ; extra == "docs"
Requires-Dist: matplotlib ; extra == "docs"
Requires-Dist: ipykernel ; extra == "docs"
Project-URL: Documentation, https://building-acoustics-tu-eindhoven.github.io/acousticDE/
Project-URL: Source, https://github.com/Building-acoustics-TU-Eindhoven/acousticDE
Project-URL: Tracker, https://github.com/Building-acoustics-TU-Eindhoven/acousticDE/issues
Provides-Extra: dev
Provides-Extra: docs
